Workbook

Sheet Assumptions
A1: Enterprise Preview Model - Core Assumptions
A2: Generated: 2026-03-02
A4: Segment | B4: Starting ARR ($) | C4: New ARR Growth / Month | D4: Churn Rate / Month | E4: Gross Margin | F4: Source URL
A5: Enterprise | B5: 7200000 | C5: 0.028 | D5: 0.009 | E5: 0.81 | F5: https://example.com/revenue-benchmark
A6: Mid-Market | B6: 4300000 | C6: 0.022 | D6: 0.011 | E6: 0.77 | F6: https://example.com/midmarket-report
A7: SMB | B7: 2400000 | C7: 0.018 | D7: 0.013 | E7: 0.71 | F7: https://example.com/smb-observatory
A8: Public Sector | B8: 1600000 | C8: 0.031 | D8: 0.008 | E8: 0.74 | F8: https://example.com/public-sector-data
A11: Global Controls
A12: Price uplift factor | B12: 0.04
A13: Efficiency gain factor | B13: 0.03
A14: Scenario selector | B14: Base

Sheet Monthly_Model
A1: Monthly ARR Waterfall (Formulas Preserved)
A3: Metric | B3: Jan-26 | C3: Feb-26 | D3: Mar-26 | E3: Apr-26 | F3: May-26 | G3: Jun-26 | H3: Jul-26 | I3: Aug-26 | J3: Sep-26 | K3: Oct-26 | L3: Nov-26 | M3: Dec-26
A5: Enterprise - Starting ARR | B5: =Assumptions!$B$5 | C5: =B8 | D5: =C8 | E5: =D8 | F5: =E8 | G5: =F8 | H5: =G8 | I5: =H8 | J5: =I8 | ... M5: =L8
A6: Enterprise - New ARR | B6: =B5*Assumptions!$C$5*(1+Assumptions!$B$12) | C6: =C5*Assumptions!$C$5*(1+Assumptions!$B$12) | D6: =D5*Assumptions!$C$5*(1+Assumptions!$B$12) | E6: =E5*Assumptions!$C$5*(1+Assumptions!$B$12) | F6: =F5*Assumptions!$C$5*(1+Assumptions!$B$12) | G6: =G5*Assumptions!$C$5*(1+Assumptions!$B$12) | H6: =H5*Assumptions!$C$5*(1+Assumptions!$B$12) | I6: =I5*Assumptions!$C$5*(1+Assumptions!$B$12) | ... M6: =M5*Assumptions!$C$5*(1+Assumptions!$B$12)
A7: Enterprise - Churn ARR | B7: =-B5*Assumptions!$D$5 | C7: =-C5*Assumptions!$D$5 | D7: =-D5*Assumptions!$D$5 | E7: =-E5*Assumptions!$D$5 | F7: =-F5*Assumptions!$D$5 | G7: =-G5*Assumptions!$D$5 | H7: =-H5*Assumptions!$D$5 | I7: =-I5*Assumptions!$D$5 | ... M7: =-M5*Assumptions!$D$5
A8: Enterprise - Ending ARR | B8: =B5+B6+B7 | C8: =C5+C6+C7 | D8: =D5+D6+D7 | E8: =E5+E6+E7 | F8: =F5+F6+F7 | G8: =G5+G6+G7 | H8: =H5+H6+H7 | I8: =I5+I6+I7 | ... M8: =M5+M6+M7
A10: Mid-Market - Starting ARR | B10: =Assumptions!$B$6 | C10: =B13 | D10: =C13 | E10: =D13 | F10: =E13 | G10: =F13 | H10: =G13 | I10: =H13 | J10: =I13 | ... M10: =L13
A11: Mid-Market - New ARR | B11: =B10*Assumptions!$C$6*(1+Assumptions!$B$12) | C11: =C10*Assumptions!$C$6*(1+Assumptions!$B$12) | D11: =D10*Assumptions!$C$6*(1+Assumptions!$B$12) | E11: =E10*Assumptions!$C$6*(1+Assumptions!$B$12) | F11: =F10*Assumptions!$C$6*(1+Assumptions!$B$12) | G11: =G10*Assumptions!$C$6*(1+Assumptions!$B$12) | H11: =H10*Assumptions!$C$6*(1+Assumptions!$B$12) | I11: =I10*Assumptions!$C$6*(1+Assumptions!$B$12) | ... M11: =M10*Assumptions!$C$6*(1+Assumptions!$B$12)
A12: Mid-Market - Churn ARR | B12: =-B10*Assumptions!$D$6 | C12: =-C10*Assumptions!$D$6 | D12: =-D10*Assumptions!$D$6 | E12: =-E10*Assumptions!$D$6 | F12: =-F10*Assumptions!$D$6 | G12: =-G10*Assumptions!$D$6 | H12: =-H10*Assumptions!$D$6 | I12: =-I10*Assumptions!$D$6 | ... M12: =-M10*Assumptions!$D$6
A13: Mid-Market - Ending ARR | B13: =B10+B11+B12 | C13: =C10+C11+C12 | D13: =D10+D11+D12 | E13: =E10+E11+E12 | F13: =F10+F11+F12 | G13: =G10+G11+G12 | H13: =H10+H11+H12 | I13: =I10+I11+I12 | ... M13: =M10+M11+M12
A15: SMB - Starting ARR | B15: =Assumptions!$B$7 | C15: =B18 | D15: =C18 | E15: =D18 | F15: =E18 | G15: =F18 | H15: =G18 | I15: =H18 | J15: =I18 | ... M15: =L18
A16: SMB - New ARR | B16: =B15*Assumptions!$C$7*(1+Assumptions!$B$12) | C16: =C15*Assumptions!$C$7*(1+Assumptions!$B$12) | D16: =D15*Assumptions!$C$7*(1+Assumptions!$B$12) | E16: =E15*Assumptions!$C$7*(1+Assumptions!$B$12) | F16: =F15*Assumptions!$C$7*(1+Assumptions!$B$12) | G16: =G15*Assumptions!$C$7*(1+Assumptions!$B$12) | H16: =H15*Assumptions!$C$7*(1+Assumptions!$B$12) | I16: =I15*Assumptions!$C$7*(1+Assumptions!$B$12) | ... M16: =M15*Assumptions!$C$7*(1+Assumptions!$B$12)
A17: SMB - Churn ARR | B17: =-B15*Assumptions!$D$7 | C17: =-C15*Assumptions!$D$7 | D17: =-D15*Assumptions!$D$7 | E17: =-E15*Assumptions!$D$7 | F17: =-F15*Assumptions!$D$7 | G17: =-G15*Assumptions!$D$7 | H17: =-H15*Assumptions!$D$7 | I17: =-I15*Assumptions!$D$7 | ... M17: =-M15*Assumptions!$D$7
A18: SMB - Ending ARR | B18: =B15+B16+B17 | C18: =C15+C16+C17 | D18: =D15+D16+D17 | E18: =E15+E16+E17 | F18: =F15+F16+F17 | G18: =G15+G16+G17 | H18: =H15+H16+H17 | I18: =I15+I16+I17 | ... M18: =M15+M16+M17
A20: Public Sector - Starting ARR | B20: =Assumptions!$B$8 | C20: =B23 | D20: =C23 | E20: =D23 | F20: =E23 | G20: =F23 | H20: =G23 | I20: =H23 | J20: =I23 | ... M20: =L23
A21: Public Sector - New ARR | B21: =B20*Assumptions!$C$8*(1+Assumptions!$B$12) | C21: =C20*Assumptions!$C$8*(1+Assumptions!$B$12) | D21: =D20*Assumptions!$C$8*(1+Assumptions!$B$12) | E21: =E20*Assumptions!$C$8*(1+Assumptions!$B$12) | F21: =F20*Assumptions!$C$8*(1+Assumptions!$B$12) | G21: =G20*Assumptions!$C$8*(1+Assumptions!$B$12) | H21: =H20*Assumptions!$C$8*(1+Assumptions!$B$12) | I21: =I20*Assumptions!$C$8*(1+Assumptions!$B$12) | ... M21: =M20*Assumptions!$C$8*(1+Assumptions!$B$12)
A22: Public Sector - Churn ARR | B22: =-B20*Assumptions!$D$8 | C22: =-C20*Assumptions!$D$8 | D22: =-D20*Assumptions!$D$8 | E22: =-E20*Assumptions!$D$8 | F22: =-F20*Assumptions!$D$8 | G22: =-G20*Assumptions!$D$8 | H22: =-H20*Assumptions!$D$8 | I22: =-I20*Assumptions!$D$8 | ... M22: =-M20*Assumptions!$D$8
A23: Public Sector - Ending ARR | B23: =B20+B21+B22 | C23: =C20+C21+C22 | D23: =D20+D21+D22 | E23: =E20+E21+E22 | F23: =F20+F21+F22 | G23: =G20+G21+G22 | H23: =H20+H21+H22 | I23: =I20+I21+I22 | ... M23: =M20+M21+M22
A26: Total Ending ARR | B26: =B8+B13+B18+B23 | C26: =C8+C13+C18+C23 | D26: =D8+D13+D18+D23 | E26: =E8+E13+E18+E23 | F26: =F8+F13+F18+F23 | G26: =G8+G13+G18+G23 | H26: =H8+H13+H18+H23 | I26: =I8+I13+I18+I23 | ... M26: =M8+M13+M18+M23
A27: Weighted Gross Margin | B27: =(B8*Assumptions!$E$5+B13*Assumptions!$E$6+B18*Assumptions!$E$7+B23*Assumptions!$E$8)/B26 | C27: =(C8*Assumptions!$E$5+C13*Assumptions!$E$6+C18*Assumptions!$E$7+C23*Assumptions!$E$8)/C26 | D27: =(D8*Assumptions!$E$5+D13*Assumptions!$E$6+D18*Assumptions!$E$7+D23*Assumptions!$E$8)/D26 | E27: =(E8*Assumptions!$E$5+E13*Assumptions!$E$6+E18*Assumptions!$E$7+E23*Assumptions!$E$8)/E26 | F27: =(F8*Assumptions!$E$5+F13*Assumptions!$E$6+F18*Assumptions!$E$7+F23*Assumptions!$E$8)/F26 | G27: =(G8*Assumptions!$E$5+G13*Assumptions!$E$6+G18*Assumptions!$E$7+G23*Assumptions!$E$8)/G26 | H27: =(H8*Assumptions!$E$5+H13*Assumptions!$E$6+H18*Assumptions!$E$7+H23*Assumptions!$E$8)/H26 | I27: =(I8*Assumptions!$E$5+I13*Assumptions!$E$6+I18*Assumptions!$E$7+I23*Assumptions!$E$8)/I26 | ... M27: =(M8*Assumptions!$E$5+M13*Assumptions!$E$6+M18*Assumptions!$E$7+M23*Assumptions!$E$8)/M26
A28: Implied EBITDA | B28: =B26*B27*(1+Assumptions!$B$13) | C28: =C26*C27*(1+Assumptions!$B$13) | D28: =D26*D27*(1+Assumptions!$B$13) | E28: =E26*E27*(1+Assumptions!$B$13) | F28: =F26*F27*(1+Assumptions!$B$13) | G28: =G26*G27*(1+Assumptions!$B$13) | H28: =H26*H27*(1+Assumptions!$B$13) | I28: =I26*I27*(1+Assumptions!$B$13) | ... M28: =M26*M27*(1+Assumptions!$B$13)
A29: Net New ARR | B29: =B26-B26 | C29: =C26-B26 | D29: =D26-C26 | E29: =E26-D26 | F29: =F26-E26 | G29: =G26-F26 | H29: =H26-G26 | I29: =I26-H26 | J29: =J26-I26 | ... M29: =M26-L26

Sheet Scenario_Analysis
A1: Scenario Engine
A3: Selected Scenario | B3: Base
A5: Metric | B5: Base | C5: Upside | D5: Downside | E5: Active Value
A6: Price uplift | B6: 0.04 | C6: 0.09 | D6: -0.02 | E6: =CHOOSE(MATCH($B$3,{"Base","Upside","Downside"},0),B6,C6,D6)
A7: New ARR acceleration | B7: 0 | C7: 0.06 | D7: -0.05 | E7: =CHOOSE(MATCH($B$3,{"Base","Upside","Downside"},0),B7,C7,D7)
A8: Churn reduction | B8: 0 | C8: 0.03 | D8: -0.02 | E8: =CHOOSE(MATCH($B$3,{"Base","Upside","Downside"},0),B8,C8,D8)
A9: Efficiency gain | B9: 0.03 | C9: 0.06 | D9: 0.01 | E9: =CHOOSE(MATCH($B$3,{"Base","Upside","Downside"},0),B9,C9,D9)
A12: Projected Dec ARR ($) | B12: =Monthly_Model!M26
A13: Projected Dec EBITDA ($) | B13: =Monthly_Model!M28
A14: ARR Delta vs Jan ($) | B14: =Monthly_Model!M26-Monthly_Model!B26

Sheet Dashboard
A1: Executive Dashboard
A3: Dec ARR | D3: Dec EBITDA | G3: ARR Growth (Jan->Dec) | J3: Avg Gross Margin
A4: =Monthly_Model!M26 | D4: =Monthly_Model!M28 | G4: =IFERROR((Monthly_Model!M26/Monthly_Model!B26)-1,0) | J4: =AVERAGE(Monthly_Model!B27:M27)
A8: Month | B8: =Monthly_Model!B3 | C8: =Monthly_Model!C3 | D8: =Monthly_Model!D3 | E8: =Monthly_Model!E3 | F8: =Monthly_Model!F3 | G8: =Monthly_Model!G3 | H8: =Monthly_Model!H3 | I8: =Monthly_Model!I3 | ... M8: =Monthly_Model!M3
A9: Total ARR | B9: =Monthly_Model!B26 | C9: =Monthly_Model!C26 | D9: =Monthly_Model!D26 | E9: =Monthly_Model!E26 | F9: =Monthly_Model!F26 | G9: =Monthly_Model!G26 | H9: =Monthly_Model!H26 | I9: =Monthly_Model!I26 | ... M9: =Monthly_Model!M26
A12: Segment | B12: Dec ARR
A13: Enterprise | B13: =Monthly_Model!M18
A14: Mid-Market | B14: =Monthly_Model!M23
A15: SMB | B15: =Monthly_Model!M28
A16: Public Sector | B16: =Monthly_Model!M33

Sheet Data_Quality
A1: Model Quality Checks
A3: Check | B3: Formula | C3: Status | D3: Details
A4: No negative ending ARR | B4: =IF(MIN(Monthly_Model!B8:M33)>=0,"PASS","FAIL") | C4: =B4 | D4: All ending ARR cells should be non-negative.
A5: Gross margin in range | B5: =IF(AND(MIN(Monthly_Model!B27:M27)>=0.6,MAX(Monthly_Model!B27:M27)<=0.9),"PASS","FAIL") | C5: =B5 | D5: Expected gross margin between 60% and 90%.
A6: Dec ARR exceeds Jan ARR | B6: =IF(Monthly_Model!M26>Monthly_Model!B26,"PASS","FAIL") | C6: =B6 | D6: Growth trajectory should be positive in base scenario.
